matrix2mpo_plus/Matrix2MPO_plus.py
matrix2mpo_plus/__init__.py
matrix2mpo_plus/libs/svd_module.cpython-310-x86_64-linux-gnu.so
matrix2mpo_plus-1.0.0.dist-info/LICENSE
matrix2mpo_plus-1.0.0.dist-info/METADATA
matrix2mpo_plus-1.0.0.dist-info/WHEEL
matrix2mpo_plus-1.0.0.dist-info/top_level.txt
matrix2mpo_plus-1.0.0.dist-info/RECORD
