Metadata-Version: 2.2
Name: matrix2mpo-plus
Version: 1.0.0
Summary: A Python package for Matrix Product Operator (MPO) decomposition
Home-page: https://github.com/your-username/matrix2mpo-plus
Author: Matrix2MPO Plus Team
Author-email: Matrix2MPO Plus Team <matrix2mpo@example.com>
Maintainer-email: Matrix2MPO Plus Team <matrix2mpo@example.com>
License: MIT
Project-URL: Homepage, https://github.com/your-username/matrix2mpo-plus
Project-URL: Documentation, https://matrix2mpo-plus.readthedocs.io/
Project-URL: Repository, https://github.com/your-username/matrix2mpo-plus.git
Project-URL: Bug Tracker, https://github.com/your-username/matrix2mpo-plus/issues
Keywords: matrix,mpo,tensor,decomposition,svd,machine learning
Classifier: Development Status :: 4 - Beta
Classifier: Intended Audience :: Developers
Classifier: Intended Audience :: Science/Research
Classifier: License :: OSI Approved :: MIT License
Classifier: Operating System :: OS Independent
Classifier: Programming Language :: Python :: 3
Classifier: Programming Language :: Python :: 3.7
Classifier: Programming Language :: Python :: 3.8
Classifier: Programming Language :: Python :: 3.9
Classifier: Programming Language :: Python :: 3.10
Classifier: Programming Language :: Python :: 3.11
Classifier: Topic :: Scientific/Engineering :: Mathematics
Classifier: Topic :: Software Development :: Libraries :: Python Modules
Requires-Python: >=3.7
License-File: LICENSE
Requires-Dist: numpy>=1.19.0
Requires-Dist: torch>=1.8.0
Provides-Extra: dev
Requires-Dist: pytest>=6.0; extra == "dev"
Requires-Dist: pytest-cov; extra == "dev"
Requires-Dist: black; extra == "dev"
Requires-Dist: flake8; extra == "dev"
Requires-Dist: mypy; extra == "dev"
Dynamic: author
Dynamic: home-page
Dynamic: requires-python
